Matrix_App/__init__.py
Matrix_App/main.py
MatrixApp-0.1.6.dist-info/METADATA
MatrixApp-0.1.6.dist-info/WHEEL
MatrixApp-0.1.6.dist-info/top_level.txt
MatrixApp-0.1.6.dist-info/RECORD
