Metadata-Version: 2.1
Name: MatrixApp
Version: 0.1.6
Requires-Dist: numpy
Requires-Dist: matplotlib
Requires-Dist: pandas
